vagranting/__init__.py
vagranting-0.0.1.dist-info/METADATA
vagranting-0.0.1.dist-info/WHEEL
vagranting-0.0.1.dist-info/top_level.txt
vagranting-0.0.1.dist-info/RECORD
